LICENSE
MANIFEST.in
README.md
flake8_has_docstring.py
requirements.txt
setup.py
flake8_has_docstring.egg-info/PKG-INFO
flake8_has_docstring.egg-info/SOURCES.txt
flake8_has_docstring.egg-info/dependency_links.txt
flake8_has_docstring.egg-info/entry_points.txt
flake8_has_docstring.egg-info/requires.txt
flake8_has_docstring.egg-info/top_level.txt