Metadata-Version: 2.1
Name: flake8-has-docstring
Version: 0.1.3
Requires-Python: >=3.10,<3.11
License-File: LICENSE
